simvi/__init__.py
simvi/model/__init__.py
simvi/model/simvi.py
simvi/module/__init__.py
simvi/module/simvi.py
simvi-0.1.2.dist-info/LICENSE
simvi-0.1.2.dist-info/METADATA
simvi-0.1.2.dist-info/WHEEL
simvi-0.1.2.dist-info/top_level.txt
simvi-0.1.2.dist-info/RECORD
