Metadata-Version: 2.1
Name: simvi
Version: 0.1.2
Summary: Spatial Interaction Modeling using Variational Inference
Home-page: https://github.com/MingzeDong/SIMVI
Author: Mingze Dong
Author-email: mingze.dong@yale.edu
License: UNKNOWN
Project-URL: Bug Tracker, https://github.com/MingzeDong/SIMVI/issues
Platform: UNKNOWN
Classifier: Programming Language :: Python :: 3
Classifier: Development Status :: 2 - Pre-Alpha
Classifier: Operating System :: OS Independent
Requires-Python: >=3.7
License-File: LICENSE
Requires-Dist: numpy
Requires-Dist: pandas
Requires-Dist: scanpy
Requires-Dist: torch
Requires-Dist: pytorch-lightning
Requires-Dist: tqdm
Requires-Dist: scvi-tools (<=0.16.2,>=0.15.0)
Requires-Dist: scikit-learn
Requires-Dist: scipy
Requires-Dist: statsmodels
Requires-Dist: anndata
Requires-Dist: torch-geometric
Requires-Dist: py-pcha
